README.md
caff.py
setup.py
caff.egg-info/PKG-INFO
caff.egg-info/SOURCES.txt
caff.egg-info/dependency_links.txt
caff.egg-info/entry_points.txt
caff.egg-info/top_level.txt