Metadata-Version: 2.1
Name: caff
Version: 0.0.1
Summary: Text to coffee morse code and coffee morse to text
Home-page: https://github.com/skar404/coffee
Author: User Name
Author-email: skar404@gmail.com
License: UNKNOWN
Platform: UNKNOWN
Classifier: Programming Language :: Python
Classifier: Programming Language :: Python :: 3
Classifier: Development Status :: 4 - Beta
Classifier: Environment :: Other Environment
Classifier: Intended Audience :: Developers
Classifier: Operating System :: OS Independent
Classifier: Topic :: Software Development :: Libraries :: Python Modules
